{
    "parent": "item/generated",
    "textures": {
        "layer0": "item/bow"
    },
    "display": {
        "thirdperson_righthand": {
            "rotation": [ -80, 260, -40 ],
            "translation": [ -1, -2, 2.5 ],
            "scale": [ 0.9, 0.9, 0.9 ]
        },
        "thirdperson_lefthand": {
            "rotation": [ -80, -280, 40 ],
            "translation": [ -1, -2, 2.5 ],
            "scale": [ 0.9, 0.9, 0.9 ]
        },
        "firstperson_righthand": {
            "rotation": [ 0, -90, 25 ],
            "translation": [ 1.13, 3.2, 1.13],
            "scale": [ 0.68, 0.68, 0.68 ]
        },
        "firstperson_lefthand": {
            "rotation": [ 0, 90, -25 ],
            "translation": [ 1.13, 3.2, 1.13],
            "scale": [ 0.68, 0.68, 0.68 ]
        }
    },
    "overrides": [
        {
            "predicate": {
                "pulling": 1
            },
            "model": "item/bow_pulling_0"
        },
        {
            "predicate": {
                "pulling": 1,
                "pull": 0.65
            },
            "model": "item/bow_pulling_1"
        },
        {
            "predicate": {
                "pulling": 1,
                "pull": 0.9
            },
            "model": "item/bow_pulling_2"
        },
		
		
        {
            "predicate": {
				"custom_model_data":2001
            },
            "model": "item/bow/stone/stone_bow"
        },
        {
            "predicate": {
				"custom_model_data":2001,
                "pulling": 1
            },
            "model": "item/bow/stone/stone_bow_pulling_0"
        },
        {
            "predicate": {
				"custom_model_data":2001,
                "pulling": 1,
                "pull": 0.65
            },
            "model": "item/bow/stone/stone_bow_pulling_1"
        },
        {
            "predicate": {
				"custom_model_data":2001,
                "pulling": 1,
                "pull": 0.9
            },
            "model": "item/bow/stone/stone_bow_pulling_2"
        },
		
		
        {
            "predicate": {
				"custom_model_data":2002
            },
            "model": "item/bow/gold/gold_bow"
        },
        {
            "predicate": {
				"custom_model_data":2002,
                "pulling": 1
            },
            "model": "item/bow/gold/gold_bow_pulling_0"
        },
        {
            "predicate": {
				"custom_model_data":2002,
                "pulling": 1,
                "pull": 0.65
            },
            "model": "item/bow/gold/gold_bow_pulling_1"
        },
        {
            "predicate": {
				"custom_model_data":2002,
                "pulling": 1,
                "pull": 0.9
            },
            "model": "item/bow/gold/gold_bow_pulling_2"
        },
		
		
        {
            "predicate": {
				"custom_model_data":2003
            },
            "model": "item/bow/iron/iron_bow"
        },
        {
            "predicate": {
				"custom_model_data":2003,
                "pulling": 1
            },
            "model": "item/bow/iron/iron_bow_pulling_0"
        },
        {
            "predicate": {
				"custom_model_data":2003,
                "pulling": 1,
                "pull": 0.65
            },
            "model": "item/bow/iron/iron_bow_pulling_1"
        },
        {
            "predicate": {
				"custom_model_data":2003,
                "pulling": 1,
                "pull": 0.9
            },
            "model": "item/bow/iron/iron_bow_pulling_2"
        },
		
		
        {
            "predicate": {
				"custom_model_data":2004
            },
            "model": "item/bow/diamond/diamond_bow"
        },
        {
            "predicate": {
				"custom_model_data":2004,
                "pulling": 1
            },
            "model": "item/bow/diamond/diamond_bow_pulling_0"
        },
        {
            "predicate": {
				"custom_model_data":2004,
                "pulling": 1,
                "pull": 0.65
            },
            "model": "item/bow/diamond/diamond_bow_pulling_1"
        },
        {
            "predicate": {
				"custom_model_data":2004,
                "pulling": 1,
                "pull": 0.9
            },
            "model": "item/bow/diamond/diamond_bow_pulling_2"
        },
		
		
        {
            "predicate": {
				"custom_model_data":2015
            },
            "model": "item/bow/copper/copper_bow"
        },
        {
            "predicate": {
				"custom_model_data":2015,
                "pulling": 1
            },
            "model": "item/bow/copper/copper_bow_pulling_0"
        },
        {
            "predicate": {
				"custom_model_data":2015,
                "pulling": 1,
                "pull": 0.65
            },
            "model": "item/bow/copper/copper_bow_pulling_1"
        },
        {
            "predicate": {
				"custom_model_data":2015,
                "pulling": 1,
                "pull": 0.9
            },
            "model": "item/bow/copper/copper_bow_pulling_2"
        },
		
		
		
        {
            "predicate": {
				"custom_model_data":2005
            },
            "model": "item/bow/windy/windy_bow"
        },
        {
            "predicate": {
				"custom_model_data":2005,
                "pulling": 1
            },
            "model": "item/bow/windy/windy_bow_pulling_0"
        },
        {
            "predicate": {
				"custom_model_data":2005,
                "pulling": 1,
                "pull": 0.65
            },
            "model": "item/bow/windy/windy_bow_pulling_1"
        },
        {
            "predicate": {
				"custom_model_data":2005,
                "pulling": 1,
                "pull": 0.9
            },
            "model": "item/bow/windy/windy_bow_pulling_2"
        },
		
		
        {
            "predicate": {
				"custom_model_data":2006
            },
            "model": "item/bow/frost/frost_bow"
        },
        {
            "predicate": {
				"custom_model_data":2006,
                "pulling": 1
            },
            "model": "item/bow/frost/frost_bow_pulling_0"
        },
        {
            "predicate": {
				"custom_model_data":2006,
                "pulling": 1,
                "pull": 0.65
            },
            "model": "item/bow/frost/frost_bow_pulling_1"
        },
        {
            "predicate": {
				"custom_model_data":2006,
                "pulling": 1,
                "pull": 0.9
            },
            "model": "item/bow/frost/frost_bow_pulling_2"
        },
		
		
        {
            "predicate": {
				"custom_model_data":2007
            },
            "model": "item/bow/ocean/ocean_bow"
        },
        {
            "predicate": {
				"custom_model_data":2007,
                "pulling": 1
            },
            "model": "item/bow/ocean/ocean_bow_pulling_0"
        },
        {
            "predicate": {
				"custom_model_data":2007,
                "pulling": 1,
                "pull": 0.65
            },
            "model": "item/bow/ocean/ocean_bow_pulling_1"
        },
        {
            "predicate": {
				"custom_model_data":2007,
                "pulling": 1,
                "pull": 0.9
            },
            "model": "item/bow/ocean/ocean_bow_pulling_2"
        },
		
		
        {
            "predicate": {
				"custom_model_data":2008
            },
            "model": "item/bow/dark/dark_bow"
        },
        {
            "predicate": {
				"custom_model_data":2008,
                "pulling": 1
            },
            "model": "item/bow/dark/dark_bow_pulling_0"
        },
        {
            "predicate": {
				"custom_model_data":2008,
                "pulling": 1,
                "pull": 0.65
            },
            "model": "item/bow/dark/dark_bow_pulling_1"
        },
        {
            "predicate": {
				"custom_model_data":2008,
                "pulling": 1,
                "pull": 0.9
            },
            "model": "item/bow/dark/dark_bow_pulling_2"
        },
		
		
        {
            "predicate": {
				"custom_model_data":2009
            },
            "model": "item/bow/hyper/hyper_bow"
        },
        {
            "predicate": {
				"custom_model_data":2009,
                "pulling": 1
            },
            "model": "item/bow/hyper/hyper_bow_pulling_0"
        },
        {
            "predicate": {
				"custom_model_data":2009,
                "pulling": 1,
                "pull": 0.65
            },
            "model": "item/bow/hyper/hyper_bow_pulling_1"
        },
        {
            "predicate": {
				"custom_model_data":2009,
                "pulling": 1,
                "pull": 0.9
            },
            "model": "item/bow/hyper/hyper_bow_pulling_2"
        },
		
		
        {
            "predicate": {
				"custom_model_data":2010
            },
            "model": "item/bow/burning/burning_bow"
        },
        {
            "predicate": {
				"custom_model_data":2010,
                "pulling": 1
            },
            "model": "item/bow/burning/burning_bow_pulling_0"
        },
        {
            "predicate": {
				"custom_model_data":2010,
                "pulling": 1,
                "pull": 0.65
            },
            "model": "item/bow/burning/burning_bow_pulling_1"
        },
        {
            "predicate": {
				"custom_model_data":2010,
                "pulling": 1,
                "pull": 0.9
            },
            "model": "item/bow/burning/burning_bow_pulling_2"
        },
		
        {
            "predicate": {
				"custom_model_data":2011
            },
            "model": "item/bow/poison/poison_bow"
        },
        {
            "predicate": {
				"custom_model_data":2011,
                "pulling": 1
            },
            "model": "item/bow/poison/poison_bow_pulling_0"
        },
        {
            "predicate": {
				"custom_model_data":2011,
                "pulling": 1,
                "pull": 0.65
            },
            "model": "item/bow/poison/poison_bow_pulling_1"
        },
        {
            "predicate": {
				"custom_model_data":2011,
                "pulling": 1,
                "pull": 0.9
            },
            "model": "item/bow/poison/poison_bow_pulling_2"
        },
		
        {
            "predicate": {
				"custom_model_data":2012
            },
            "model": "item/bow/natural/natural_bow"
        },
        {
            "predicate": {
				"custom_model_data":2012,
                "pulling": 1
            },
            "model": "item/bow/natural/natural_bow_pulling_0"
        },
        {
            "predicate": {
				"custom_model_data":2012,
                "pulling": 1,
                "pull": 0.65
            },
            "model": "item/bow/natural/natural_bow_pulling_1"
        },
        {
            "predicate": {
				"custom_model_data":2012,
                "pulling": 1,
                "pull": 0.9
            },
            "model": "item/bow/natural/natural_bow_pulling_2"
        },
		
        {
            "predicate": {
				"custom_model_data":2014
            },
            "model": "item/bow/earth/earth_bow"
        },
        {
            "predicate": {
				"custom_model_data":2014,
                "pulling": 1
            },
            "model": "item/bow/earth/earth_bow_pulling_0"
        },
        {
            "predicate": {
				"custom_model_data":2014,
                "pulling": 1,
                "pull": 0.65
            },
            "model": "item/bow/earth/earth_bow_pulling_1"
        },
        {
            "predicate": {
				"custom_model_data":2014,
                "pulling": 1,
                "pull": 0.9
            },
            "model": "item/bow/earth/earth_bow_pulling_2"
        },
		
		
        {
            "predicate": {
				"custom_model_data":2060
            },
            "model": "item/bow/netherite/netherite_bow"
        },
        {
            "predicate": {
				"custom_model_data":2060,
                "pulling": 1
            },
            "model": "item/bow/netherite/netherite_bow_pulling_0"
        },
        {
            "predicate": {
				"custom_model_data":2060,
                "pulling": 1,
                "pull": 0.65
            },
            "model": "item/bow/netherite/netherite_bow_pulling_1"
        },
        {
            "predicate": {
				"custom_model_data":2060,
                "pulling": 1,
                "pull": 0.9
            },
            "model": "item/bow/netherite/netherite_bow_pulling_2"
        },
		
		
        {
            "predicate": {
				"custom_model_data":2101
            },
            "model": "item/bow/growing/lev1/lev1_bow"
        },
        {
            "predicate": {
				"custom_model_data":2101,
                "pulling": 1
            },
            "model": "item/bow/growing/lev1/lev1_bow_pulling_0"
        },
        {
            "predicate": {
				"custom_model_data":2101,
                "pulling": 1,
                "pull": 0.65
            },
            "model": "item/bow/growing/lev1/lev1_bow_pulling_1"
        },
        {
            "predicate": {
				"custom_model_data":2101,
                "pulling": 1,
                "pull": 0.9
            },
            "model": "item/bow/growing/lev1/lev1_bow_pulling_2"
        },
		
		
		
        {
            "predicate": {
				"custom_model_data":2102
            },
            "model": "item/bow/growing/lev2/lev2_bow"
        },
        {
            "predicate": {
				"custom_model_data":2102,
                "pulling": 1
            },
            "model": "item/bow/growing/lev2/lev2_bow_pulling_0"
        },
        {
            "predicate": {
				"custom_model_data":2102,
                "pulling": 1,
                "pull": 0.65
            },
            "model": "item/bow/growing/lev2/lev2_bow_pulling_1"
        },
        {
            "predicate": {
				"custom_model_data":2102,
                "pulling": 1,
                "pull": 0.9
            },
            "model": "item/bow/growing/lev2/lev2_bow_pulling_2"
        },
		
		
		
        {
            "predicate": {
				"custom_model_data":2103
            },
            "model": "item/bow/growing/lev3/lev3_bow"
        },
        {
            "predicate": {
				"custom_model_data":2103,
                "pulling": 1
            },
            "model": "item/bow/growing/lev3/lev3_bow_pulling_0"
        },
        {
            "predicate": {
				"custom_model_data":2103,
                "pulling": 1,
                "pull": 0.65
            },
            "model": "item/bow/growing/lev3/lev3_bow_pulling_1"
        },
        {
            "predicate": {
				"custom_model_data":2103,
                "pulling": 1,
                "pull": 0.9
            },
            "model": "item/bow/growing/lev3/lev3_bow_pulling_2"
        },
		
		
        {
            "predicate": {
				"custom_model_data":2104
            },
            "model": "item/bow/growing/lev4/lev4_bow"
        },
        {
            "predicate": {
				"custom_model_data":2104,
                "pulling": 1
            },
            "model": "item/bow/growing/lev4/lev4_bow_pulling_0"
        },
        {
            "predicate": {
				"custom_model_data":2104,
                "pulling": 1,
                "pull": 0.65
            },
            "model": "item/bow/growing/lev4/lev4_bow_pulling_1"
        },
        {
            "predicate": {
				"custom_model_data":2104,
                "pulling": 1,
                "pull": 0.9
            },
            "model": "item/bow/growing/lev4/lev4_bow_pulling_2"
        },
		
		
		
        {
            "predicate": {
				"custom_model_data":2105
            },
            "model": "item/bow/growing/lev5/lev5_bow"
        },
        {
            "predicate": {
				"custom_model_data":2105,
                "pulling": 1
            },
            "model": "item/bow/growing/lev5/lev5_bow_pulling_0"
        },
        {
            "predicate": {
				"custom_model_data":2105,
                "pulling": 1,
                "pull": 0.65
            },
            "model": "item/bow/growing/lev5/lev5_bow_pulling_1"
        },
        {
            "predicate": {
				"custom_model_data":2105,
                "pulling": 1,
                "pull": 0.9
            },
            "model": "item/bow/growing/lev5/lev5_bow_pulling_2"
        },
		
		
		
        {
            "predicate": {
				"custom_model_data":2106
            },
            "model": "item/bow/growing/lev6/lev6_bow"
        },
        {
            "predicate": {
				"custom_model_data":2106,
                "pulling": 1
            },
            "model": "item/bow/growing/lev6/lev6_bow_pulling_0"
        },
        {
            "predicate": {
				"custom_model_data":2106,
                "pulling": 1,
                "pull": 0.65
            },
            "model": "item/bow/growing/lev6/lev6_bow_pulling_1"
        },
        {
            "predicate": {
				"custom_model_data":2106,
                "pulling": 1,
                "pull": 0.9
            },
            "model": "item/bow/growing/lev6/lev6_bow_pulling_2"
        },
		
		
		
        {
            "predicate": {
				"custom_model_data":2107
            },
            "model": "item/bow/growing/lev7/lev7_bow"
        },
        {
            "predicate": {
				"custom_model_data":2107,
                "pulling": 1
            },
            "model": "item/bow/growing/lev7/lev7_bow_pulling_0"
        },
        {
            "predicate": {
				"custom_model_data":2107,
                "pulling": 1,
                "pull": 0.65
            },
            "model": "item/bow/growing/lev7/lev7_bow_pulling_1"
        },
        {
            "predicate": {
				"custom_model_data":2107,
                "pulling": 1,
                "pull": 0.9
            },
            "model": "item/bow/growing/lev7/lev7_bow_pulling_2"
        },
		
		
		
        {
            "predicate": {
				"custom_model_data":2108
            },
            "model": "item/bow/growing/lev8/lev8_bow"
        },
        {
            "predicate": {
				"custom_model_data":2108,
                "pulling": 1
            },
            "model": "item/bow/growing/lev8/lev8_bow_pulling_0"
        },
        {
            "predicate": {
				"custom_model_data":2108,
                "pulling": 1,
                "pull": 0.65
            },
            "model": "item/bow/growing/lev8/lev8_bow_pulling_1"
        },
        {
            "predicate": {
				"custom_model_data":2108,
                "pulling": 1,
                "pull": 0.9
            },
            "model": "item/bow/growing/lev8/lev8_bow_pulling_2"
        }
		
		
    ]
}
